Metadata-Version: 1.1
Name: stadista
Version: 0.1
Summary: Toolbox to work with several platforms's data such as Youtube's stats
Home-page: https://github.com/Tester86/stadista
Author: Tester86
Author-email: tester86t@gmail.com
License: MIT
Download-URL: https://github.com/Tester86/passfactory/stadista.py/v_01.tar.gz
Keywords: STATS,TOOLBOX,PROBABILITY
Platform: UNKNOWN
Classifier: Development Status :: 4 - Beta
Classifier: Intended Audience :: Developers
Classifier: Topic :: Software Development :: Build Tools
Classifier: License :: OSI Approved :: MIT License
Classifier: Programming Language :: Python :: 3
Classifier: Programming Language :: Python :: 3.4
Classifier: Programming Language :: Python :: 3.5
Classifier: Programming Language :: Python :: 3.6
